voice_cloning/__init__.py
voice_cloning/generation.py
voice_cloning/encoder/__init__.py
voice_cloning/encoder/audio.py
voice_cloning/encoder/config.py
voice_cloning/encoder/inference.py
voice_cloning/encoder/model.py
voice_cloning/encoder/params_data.py
voice_cloning/encoder/params_model.py
voice_cloning/encoder/preprocess.py
voice_cloning/encoder/train.py
voice_cloning/encoder/visualizations.py
voice_cloning/encoder/data_objects/__init__.py
voice_cloning/encoder/data_objects/random_cycler.py
voice_cloning/encoder/data_objects/speaker.py
voice_cloning/encoder/data_objects/speaker_batch.py
voice_cloning/encoder/data_objects/speaker_verification_dataset.py
voice_cloning/encoder/data_objects/utterance.py
voice_cloning/speakers/speaker_library.xlsx
voice_cloning/speakers/indian/female/voice1.wav
voice_cloning/speakers/indian/female/voice2.wav
voice_cloning/speakers/indian/female/voice3.wav
voice_cloning/speakers/indian/female/voice4.wav
voice_cloning/speakers/indian/female/voice5.wav
voice_cloning/speakers/indian/male/voice1.wav
voice_cloning/speakers/indian/male/voice2.wav
voice_cloning/speakers/indian/male/voice3.wav
voice_cloning/speakers/indian/male/voice4.wav
voice_cloning/speakers/indian/male/voice5.wav
voice_cloning/speakers/indian/male/voice6.wav
voice_cloning/speakers/western/female/voice1.wav
voice_cloning/speakers/western/female/voice10.wav
voice_cloning/speakers/western/female/voice2.wav
voice_cloning/speakers/western/female/voice3.wav
voice_cloning/speakers/western/female/voice4.wav
voice_cloning/speakers/western/female/voice5.wav
voice_cloning/speakers/western/female/voice6.wav
voice_cloning/speakers/western/female/voice7.wav
voice_cloning/speakers/western/female/voice8.wav
voice_cloning/speakers/western/female/voice9.wav
voice_cloning/speakers/western/male/voice1.wav
voice_cloning/speakers/western/male/voice10.wav
voice_cloning/speakers/western/male/voice2.wav
voice_cloning/speakers/western/male/voice3.wav
voice_cloning/speakers/western/male/voice4.wav
Voice_Cloning-0.0.9.dist-info/METADATA
Voice_Cloning-0.0.9.dist-info/WHEEL
Voice_Cloning-0.0.9.dist-info/top_level.txt
Voice_Cloning-0.0.9.dist-info/RECORD
