Metadata-Version: 2.1
Name: Voice-Cloning
Version: 0.0.9
Summary: Introducing Voice_Cloning: A Python Package for Speech Synthesis and Voice Cloning!
Home-page: https://github.com/dreji18/Voice_Cloning
Author: Deepak John Reji
Author-email: deepakjohn1994@gmail.com
License: MIT
Platform: UNKNOWN
Classifier: License :: OSI Approved :: MIT License
Classifier: Programming Language :: Python :: 3.7
Classifier: Programming Language :: Python :: 3.8
Classifier: Programming Language :: Python :: 3.9
Requires-Dist: inflect (==5.3.0)
Requires-Dist: librosa (==0.8.1)
Requires-Dist: matplotlib
Requires-Dist: numpy
Requires-Dist: Pillow
Requires-Dist: scikit-learn
Requires-Dist: scipy
Requires-Dist: sounddevice
Requires-Dist: SoundFile
Requires-Dist: tqdm
Requires-Dist: umap-learn
Requires-Dist: Unidecode
Requires-Dist: urllib3
Requires-Dist: visdom
Requires-Dist: webrtcvad
Requires-Dist: noisereduce
Requires-Dist: torch
